{
  "modules": [
    {
      "module_name": "PhotoSwipe Gallery",
      "elements": [
        {
          "element_description": "Close button for PhotoSwipe",
          "locators": [
            {
              "strategy": "css selector",
              "value": ".pswp__button--close",
              "priority": 1,
              "reason": "Specific class for the close button makes it unique and easy to target."
            }
          ]
        },
        {
          "element_description": "Share button for PhotoSwipe",
          "locators": [
            {
              "strategy": "css selector",
              "value": ".pswp__button--share",
              "priority": 1,
              "reason": "Specific class for the share button makes it unique and easy to target."
            }
          ]
        },
        {
          "element_description": "Toggle fullscreen button for PhotoSwipe",
          "locators": [
            {
              "strategy": "css selector",
              "value": ".pswp__button--fs",
              "priority": 1,
              "reason": "Specific class for the fullscreen button makes it unique and easy to target."
            }
          ]
        },
        {
          "element_description": "Zoom button for PhotoSwipe",
          "locators": [
            {
              "strategy": "css selector",
              "value": ".pswp__button--zoom",
              "priority": 1,
              "reason": "Specific class for the zoom button makes it unique and easy to target."
            }
          ]
        },
        {
          "element_description": "Previous button for PhotoSwipe",
          "locators": [
            {
              "strategy": "css selector",
              "value": ".pswp__button--arrow--left",
              "priority": 1,
              "reason": "Specific class for the previous button makes it unique and easy to target."
            }
          ]
        },
        {
          "element_description": "Next button for PhotoSwipe",
          "locators": [
            {
              "strategy": "css selector",
              "value": ".pswp__button--arrow--right",
              "priority": 1,
              "reason": "Specific class for the next button makes it unique and easy to target."
            }
          ]
        }
      ]
    },
    {
      "module_name": "NProgress",
      "elements": [
        {
          "element_description": "NProgress bar",
          "locators": [
            {
              "strategy": "css selector",
              "value": "#nprogress .bar",
              "priority": 1,
              "reason": "The ID of the parent element combined with the class of the bar makes it a unique target."
            }
          ]
        }
      ]
    }
  ]
}